segysak/__init__.py
segysak/_accessor.py
segysak/_cli.py
segysak/_core.py
segysak/_keyfield.py
segysak/_richstr.py
segysak/_seismic_dataset.py
segysak/_version.py
segysak/geometry.py
segysak/progress.py
segysak/seisnc.py
segysak/tools.py
segysak/segy/__init__.py
segysak/segy/_segy_core.py
segysak/segy/_segy_freewriter.py
segysak/segy/_segy_globals.py
segysak/segy/_segy_headers.py
segysak/segy/_segy_knownbytes.py
segysak/segy/_segy_loader.py
segysak/segy/_segy_text.py
segysak/segy/_segy_writer.py
segysak/segy/_xarray.py
segysak/segy/_xarray_writer.py
segysak-0.5.4.dist-info/METADATA
segysak-0.5.4.dist-info/WHEEL
segysak-0.5.4.dist-info/entry_points.txt
segysak-0.5.4.dist-info/licenses/LICENSE
segysak-0.5.4.dist-info/RECORD
