Metadata-Version: 2.3
Name: segysak
Version: 0.5.4
Summary: SEG-Y Seismic Data Inspection and Manipulation Tools using Xarray
Project-URL: Repository, https://github.com/trhallam/segysak
Author-email: SEGY-SAK Developers <segysak@gamil.com>
License:                     GNU GENERAL PUBLIC LICENSE
License-File: LICENSE
Classifier: Development Status :: 5 - Production/Stable
Classifier: License :: OSI Approved :: GNU General Public License v3 (GPLv3)
Classifier: Natural Language :: English
Classifier: Operating System :: OS Independent
Classifier: Programming Language :: Python :: 3 :: Only
Classifier: Topic :: Scientific/Engineering
Requires-Python: >=3.9
Requires-Dist: addict
Requires-Dist: click
Requires-Dist: dask
Requires-Dist: distributed
Requires-Dist: h5netcdf
Requires-Dist: loguru
Requires-Dist: matplotlib
Requires-Dist: more-itertools>=8.0
Requires-Dist: numpy>=1.20
Requires-Dist: pandas
Requires-Dist: scipy!=1.10.0
Requires-Dist: segyio
Requires-Dist: tqdm
Requires-Dist: typing-extensions
Requires-Dist: xarray
Provides-Extra: docs
Requires-Dist: cffconvert; extra == 'docs'
Requires-Dist: ipywidgets; extra == 'docs'
Requires-Dist: jupyterlab; extra == 'docs'
Requires-Dist: jupytext; extra == 'docs'
Requires-Dist: mike; extra == 'docs'
Requires-Dist: mkautodoc; extra == 'docs'
Requires-Dist: mkdocs; extra == 'docs'
Requires-Dist: mkdocs-include-markdown-plugin; extra == 'docs'
Requires-Dist: mkdocs-jupyter; extra == 'docs'
Requires-Dist: mkdocs-material; extra == 'docs'
Requires-Dist: mkdocs-simple-plugin; extra == 'docs'
Requires-Dist: mkdocstrings; extra == 'docs'
Requires-Dist: mkdocstrings-python; extra == 'docs'
Requires-Dist: pyshp; extra == 'docs'
Requires-Dist: pyvista; extra == 'docs'
Requires-Dist: wellpathpy; extra == 'docs'
Provides-Extra: test
Requires-Dist: affine; extra == 'test'
Requires-Dist: hypothesis; extra == 'test'
Requires-Dist: pylint; extra == 'test'
Requires-Dist: pytest; extra == 'test'
